flash_attn_config.py
flash_attn_interface.py
flash_attn_3-0.0.0.dist-info/METADATA
flash_attn_3-0.0.0.dist-info/WHEEL
flash_attn_3-0.0.0.dist-info/top_level.txt
flash_attn_3-0.0.0.dist-info/RECORD
