Metadata-Version: 2.4
Name: flash_attn_3
Version: 0.0.0
Summary: FlashAttention-3
License: BSD-3-Clause
Keywords: one,two
Classifier: Programming Language :: Python :: 3
Classifier: License :: OSI Approved :: Apache Software License
Classifier: Operating System :: Unix
Requires-Python: >=3.8
Requires-Dist: torch
Requires-Dist: einops
Requires-Dist: packaging
Requires-Dist: ninja
